ovos_stt_plugin_nemo/__init__.py
ovos_stt_plugin_nemo/version.py
ovos_stt_plugin_nemo-0.2.5.dist-info/LICENSE
ovos_stt_plugin_nemo-0.2.5.dist-info/METADATA
ovos_stt_plugin_nemo-0.2.5.dist-info/WHEEL
ovos_stt_plugin_nemo-0.2.5.dist-info/entry_points.txt
ovos_stt_plugin_nemo-0.2.5.dist-info/top_level.txt
ovos_stt_plugin_nemo-0.2.5.dist-info/zip-safe
ovos_stt_plugin_nemo-0.2.5.dist-info/RECORD
